uwdtool/__init__.py
uwdtool/BinaryReader.py
uwdtool/brotli/brotli.cp310-win32.pyd
uwdtool/brotli/brotli.cp310-win_amd64.pyd
uwdtool/brotli/brotli.cp311-win32.pyd
uwdtool/brotli/brotli.cp311-win_amd64.pyd
uwdtool/brotli/brotli.cp312-win32.pyd
uwdtool/brotli/brotli.cp312-win_amd64.pyd
uwdtool/brotli/brotli.cp313-win32.pyd
uwdtool/brotli/brotli.cp313-win_amd64.pyd
uwdtool/brotli/brotli.cp38-win32.pyd
uwdtool/brotli/brotli.cp38-win_amd64.pyd
uwdtool/brotli/brotli.cp39-win32.pyd
uwdtool/brotli/brotli.cp39-win_amd64.pyd
uwdtool/Common.py
uwdtool/CompressionManager.py
uwdtool/Inspector.py
uwdtool/Packer.py
uwdtool/UnityWebData.py
uwdtool/Unpacker.py
uwdtool/UWDTool.py
uwdtool-1.3.0.dist-info/entry_points.txt
uwdtool-1.3.0.dist-info/METADATA
uwdtool-1.3.0.dist-info/WHEEL
uwdtool-1.3.0.dist-info/RECORD
