Metadata-Version: 2.3
Name: uwdtool
Version: 1.3.0
Summary: The tool to pack and unpack UnityWebData 1.0 files
Author: akio7624
Requires-Python: >=3.8,<=3.13
Classifier: Programming Language :: Python :: 3
Classifier: Programming Language :: Python :: 3.8
Classifier: Programming Language :: Python :: 3.9
Classifier: Programming Language :: Python :: 3.10
Classifier: Programming Language :: Python :: 3.11
Classifier: Programming Language :: Python :: 3.12
Classifier: Programming Language :: Python :: 3.13
